{
  "dataset_revision": "eea2b4fe26a775864c896887d910b76a8098ad3f",
  "mteb_dataset_name": "STS22",
  "mteb_version": "1.1.2",
  "test": {
    "en": {
      "cos_sim": {
        "pearson": 0.6838278443932333,
        "spearman": 0.6912120322377331
      },
      "euclidean": {
        "pearson": 0.7045500168848943,
        "spearman": 0.6932222780408773
      },
      "manhattan": {
        "pearson": 0.7034241625323455,
        "spearman": 0.6887321865040565
      }
    },
    "evaluation_time": 0.05
  }
}