{
  "dataset_revision": "90fceea13679c63fe563ded68f3b6f06e50061de",
  "mteb_dataset_name": "CQADupstackMathematicaRetrieval",
  "mteb_version": "1.2.0",
  "test": {
    "evaluation_time": 3.2,
    "map_at_1": 0.18751,
    "map_at_10": 0.27696,
    "map_at_100": 0.2897,
    "map_at_1000": 0.29096,
    "map_at_3": 0.24974,
    "map_at_5": 0.26548,
    "mrr_at_1": 0.2301,
    "mrr_at_10": 0.32536,
    "mrr_at_100": 0.33483,
    "mrr_at_1000": 0.33545,
    "mrr_at_3": 0.2983,
    "mrr_at_5": 0.31441,
    "ndcg_at_1": 0.2301,
    "ndcg_at_10": 0.33377,
    "ndcg_at_100": 0.39242,
    "ndcg_at_1000": 0.42047,
    "ndcg_at_3": 0.28445,
    "ndcg_at_5": 0.30851,
    "precision_at_1": 0.2301,
    "precision_at_10": 0.06119,
    "precision_at_100": 0.01044,
    "precision_at_1000": 0.00143,
    "precision_at_3": 0.1393,
    "precision_at_5": 0.101,
    "recall_at_1": 0.18751,
    "recall_at_10": 0.45975,
    "recall_at_100": 0.71296,
    "recall_at_1000": 0.91164,
    "recall_at_3": 0.32443,
    "recall_at_5": 0.3848
  }
}