{
  "dataset_revision": "c22ab2a51041ffd869aaddef7af8d8215647e41a",
  "mteb_dataset_name": "ArguAna",
  "mteb_version": "1.2.0",
  "test": {
    "evaluation_time": 15.5,
    "map_at_1": 0.38051,
    "map_at_10": 0.55254,
    "map_at_100": 0.55798,
    "map_at_1000": 0.55801,
    "map_at_3": 0.51091,
    "map_at_5": 0.53711,
    "mrr_at_1": 0.38762,
    "mrr_at_10": 0.55541,
    "mrr_at_100": 0.56079,
    "mrr_at_1000": 0.56082,
    "mrr_at_3": 0.51458,
    "mrr_at_5": 0.53944,
    "ndcg_at_1": 0.38051,
    "ndcg_at_10": 0.63725,
    "ndcg_at_100": 0.65859,
    "ndcg_at_1000": 0.65919,
    "ndcg_at_3": 0.5529,
    "ndcg_at_5": 0.59994,
    "precision_at_1": 0.38051,
    "precision_at_10": 0.09033,
    "precision_at_100": 0.00992,
    "precision_at_1000": 0.001,
    "precision_at_3": 0.22475,
    "precision_at_5": 0.15761,
    "recall_at_1": 0.38051,
    "recall_at_10": 0.90327,
    "recall_at_100": 0.99218,
    "recall_at_1000": 0.99644,
    "recall_at_3": 0.67425,
    "recall_at_5": 0.78805
  }
}