{
  "dataset_revision": null,
  "mteb_dataset_name": "SciFact",
  "mteb_version": "1.1.2",
  "test": {
    "evaluation_time": 0.67,
    "map_at_1": 0.61761,
    "map_at_10": 0.71396,
    "map_at_100": 0.71756,
    "map_at_1000": 0.71779,
    "map_at_3": 0.68024,
    "map_at_5": 0.70135,
    "mrr_at_1": 0.64667,
    "mrr_at_10": 0.72341,
    "mrr_at_100": 0.726,
    "mrr_at_1000": 0.72622,
    "mrr_at_3": 0.69722,
    "mrr_at_5": 0.71539,
    "ndcg_at_1": 0.64667,
    "ndcg_at_10": 0.75979,
    "ndcg_at_100": 0.77573,
    "ndcg_at_1000": 0.78053,
    "ndcg_at_3": 0.70268,
    "ndcg_at_5": 0.73521,
    "precision_at_1": 0.64667,
    "precision_at_10": 0.101,
    "precision_at_100": 0.01093,
    "precision_at_1000": 0.00113,
    "precision_at_3": 0.27,
    "precision_at_5": 0.18333,
    "recall_at_1": 0.61761,
    "recall_at_10": 0.89156,
    "recall_at_100": 0.965,
    "recall_at_1000": 1.0,
    "recall_at_3": 0.74089,
    "recall_at_5": 0.82078
  }
}