{
  "dataset_revision": "ec0fa4fe99da2ff19ca1214b7966684033a58814",
  "mteb_dataset_name": "NFCorpus",
  "mteb_version": "1.2.0",
  "test": {
    "evaluation_time": 1.09,
    "map_at_1": 0.07286,
    "map_at_10": 0.15229,
    "map_at_100": 0.19581,
    "map_at_1000": 0.2123,
    "map_at_3": 0.11304,
    "map_at_5": 0.12911,
    "mrr_at_1": 0.50464,
    "mrr_at_10": 0.58542,
    "mrr_at_100": 0.59163,
    "mrr_at_1000": 0.59196,
    "mrr_at_3": 0.5614,
    "mrr_at_5": 0.5789,
    "ndcg_at_1": 0.48916,
    "ndcg_at_10": 0.3839,
    "ndcg_at_100": 0.36153,
    "ndcg_at_1000": 0.45214,
    "ndcg_at_3": 0.43536,
    "ndcg_at_5": 0.41153,
    "precision_at_1": 0.50464,
    "precision_at_10": 0.2805,
    "precision_at_100": 0.09099,
    "precision_at_1000": 0.02241,
    "precision_at_3": 0.39938,
    "precision_at_5": 0.34923,
    "recall_at_1": 0.07286,
    "recall_at_10": 0.19386,
    "recall_at_100": 0.36709,
    "recall_at_1000": 0.69592,
    "recall_at_3": 0.12209,
    "recall_at_5": 0.14828
  }
}