{
  "dataset_revision": "c22ab2a51041ffd869aaddef7af8d8215647e41a",
  "mteb_dataset_name": "ArguAna",
  "mteb_version": "1.2.0",
  "test": {
    "evaluation_time": 3.0,
    "map_at_1": 0.37553,
    "map_at_10": 0.545,
    "map_at_100": 0.55057,
    "map_at_1000": 0.5506,
    "map_at_3": 0.50107,
    "map_at_5": 0.52856,
    "mrr_at_1": 0.38478,
    "mrr_at_10": 0.54828,
    "mrr_at_100": 0.55379,
    "mrr_at_1000": 0.55382,
    "mrr_at_3": 0.50533,
    "mrr_at_5": 0.53154,
    "ndcg_at_1": 0.37553,
    "ndcg_at_10": 0.63122,
    "ndcg_at_100": 0.65284,
    "ndcg_at_1000": 0.65343,
    "ndcg_at_3": 0.54275,
    "ndcg_at_5": 0.59182,
    "precision_at_1": 0.37553,
    "precision_at_10": 0.09026,
    "precision_at_100": 0.00992,
    "precision_at_1000": 0.001,
    "precision_at_3": 0.22119,
    "precision_at_5": 0.15633,
    "recall_at_1": 0.37553,
    "recall_at_10": 0.90256,
    "recall_at_100": 0.99218,
    "recall_at_1000": 0.99644,
    "recall_at_3": 0.66358,
    "recall_at_5": 0.78165
  }
}