{
  "dataset_revision": "c22ab2a51041ffd869aaddef7af8d8215647e41a",
  "mteb_dataset_name": "ArguAna",
  "mteb_version": "1.2.0",
  "test": {
    "evaluation_time": 3.14,
    "map_at_1": 0.30868,
    "map_at_10": 0.47786,
    "map_at_100": 0.48555,
    "map_at_1000": 0.48558,
    "map_at_3": 0.42888,
    "map_at_5": 0.45676,
    "mrr_at_1": 0.31579,
    "mrr_at_10": 0.48074,
    "mrr_at_100": 0.48844,
    "mrr_at_1000": 0.48847,
    "mrr_at_3": 0.43184,
    "mrr_at_5": 0.45944,
    "ndcg_at_1": 0.30868,
    "ndcg_at_10": 0.57021,
    "ndcg_at_100": 0.60063,
    "ndcg_at_1000": 0.6013,
    "ndcg_at_3": 0.46933,
    "ndcg_at_5": 0.5198,
    "precision_at_1": 0.30868,
    "precision_at_10": 0.08642,
    "precision_at_100": 0.00991,
    "precision_at_1000": 0.001,
    "precision_at_3": 0.19559,
    "precision_at_5": 0.14196,
    "recall_at_1": 0.30868,
    "recall_at_10": 0.86415,
    "recall_at_100": 0.99147,
    "recall_at_1000": 0.99644,
    "recall_at_3": 0.58677,
    "recall_at_5": 0.70982
  }
}