{
  "dataset_revision": null,
  "mteb_dataset_name": "ArguAna",
  "mteb_version": "1.1.2",
  "test": {
    "evaluation_time": 1.27,
    "map_at_1": 0.38691,
    "map_at_10": 0.54639,
    "map_at_100": 0.55227,
    "map_at_1000": 0.55231,
    "map_at_3": 0.50628,
    "map_at_5": 0.53036,
    "mrr_at_1": 0.39189,
    "mrr_at_10": 0.54826,
    "mrr_at_100": 0.5542,
    "mrr_at_1000": 0.55424,
    "mrr_at_3": 0.5083,
    "mrr_at_5": 0.5323,
    "ndcg_at_1": 0.38691,
    "ndcg_at_10": 0.62826,
    "ndcg_at_100": 0.6523,
    "ndcg_at_1000": 0.65331,
    "ndcg_at_3": 0.54657,
    "ndcg_at_5": 0.58994,
    "precision_at_1": 0.38691,
    "precision_at_10": 0.08862,
    "precision_at_100": 0.00989,
    "precision_at_1000": 0.001,
    "precision_at_3": 0.22119,
    "precision_at_5": 0.15377,
    "recall_at_1": 0.38691,
    "recall_at_10": 0.8862,
    "recall_at_100": 0.98862,
    "recall_at_1000": 0.99644,
    "recall_at_3": 0.66358,
    "recall_at_5": 0.76885
  }
}