{
  "dataset_revision": null,
  "mteb_dataset_name": "CQADupstackGisRetrieval",
  "mteb_version": "1.1.2",
  "test": {
    "evaluation_time": 30.29,
    "map_at_1": 0.29203,
    "map_at_10": 0.3861,
    "map_at_100": 0.39766,
    "map_at_1000": 0.39831,
    "map_at_3": 0.36018,
    "map_at_5": 0.37605,
    "mrr_at_1": 0.31299,
    "mrr_at_10": 0.40716,
    "mrr_at_100": 0.41691,
    "mrr_at_1000": 0.41738,
    "mrr_at_3": 0.38399,
    "mrr_at_5": 0.398,
    "ndcg_at_1": 0.31299,
    "ndcg_at_10": 0.43702,
    "ndcg_at_100": 0.49047,
    "ndcg_at_1000": 0.50691,
    "ndcg_at_3": 0.38809,
    "ndcg_at_5": 0.41403,
    "precision_at_1": 0.31299,
    "precision_at_10": 0.06576,
    "precision_at_100": 0.00969,
    "precision_at_1000": 0.00114,
    "precision_at_3": 0.1646,
    "precision_at_5": 0.11345,
    "recall_at_1": 0.29203,
    "recall_at_10": 0.57181,
    "recall_at_100": 0.81131,
    "recall_at_1000": 0.93461,
    "recall_at_3": 0.44062,
    "recall_at_5": 0.50331
  }
}