{
  "dataset_revision": null,
  "mteb_dataset_name": "ArguAna",
  "mteb_version": "1.1.2",
  "test": {
    "evaluation_time": 1.64,
    "map_at_1": 0.32219,
    "map_at_10": 0.4932,
    "map_at_100": 0.50014,
    "map_at_1000": 0.50018,
    "map_at_3": 0.44452,
    "map_at_5": 0.47422,
    "mrr_at_1": 0.32788,
    "mrr_at_10": 0.49528,
    "mrr_at_100": 0.50221,
    "mrr_at_1000": 0.50225,
    "mrr_at_3": 0.44654,
    "mrr_at_5": 0.4763,
    "ndcg_at_1": 0.32219,
    "ndcg_at_10": 0.58438,
    "ndcg_at_100": 0.61222,
    "ndcg_at_1000": 0.61301,
    "ndcg_at_3": 0.48536,
    "ndcg_at_5": 0.53893,
    "precision_at_1": 0.32219,
    "precision_at_10": 0.08734,
    "precision_at_100": 0.00991,
    "precision_at_1000": 0.001,
    "precision_at_3": 0.20128,
    "precision_at_5": 0.1468,
    "recall_at_1": 0.32219,
    "recall_at_10": 0.8734,
    "recall_at_100": 0.99075,
    "recall_at_1000": 0.99644,
    "recall_at_3": 0.60384,
    "recall_at_5": 0.734
  }
}