{
  "dataset_revision": "160c094312a0e1facb97e55eeddb698c0abe3571",
  "mteb_dataset_name": "CQADupstackWebmastersRetrieval",
  "mteb_version": "1.2.0",
  "test": {
    "evaluation_time": 3.12,
    "map_at_1": 0.27535,
    "map_at_10": 0.37769,
    "map_at_100": 0.39377,
    "map_at_1000": 0.39602,
    "map_at_3": 0.34409,
    "map_at_5": 0.36136,
    "mrr_at_1": 0.33202,
    "mrr_at_10": 0.42727,
    "mrr_at_100": 0.43677,
    "mrr_at_1000": 0.4371,
    "mrr_at_3": 0.4025,
    "mrr_at_5": 0.41673,
    "ndcg_at_1": 0.33202,
    "ndcg_at_10": 0.44167,
    "ndcg_at_100": 0.50035,
    "ndcg_at_1000": 0.52105,
    "ndcg_at_3": 0.38992,
    "ndcg_at_5": 0.41196,
    "precision_at_1": 0.33202,
    "precision_at_10": 0.08498,
    "precision_at_100": 0.01656,
    "precision_at_1000": 0.0025,
    "precision_at_3": 0.18445,
    "precision_at_5": 0.13162,
    "recall_at_1": 0.27535,
    "recall_at_10": 0.56366,
    "recall_at_100": 0.82911,
    "recall_at_1000": 0.95444,
    "recall_at_3": 0.41658,
    "recall_at_5": 0.47754
  }
}