{
  "dataset_revision": "f46a197baaae43b4f621051089b82a364682dfeb",
  "mteb_dataset_name": "CQADupstackAndroidRetrieval",
  "mteb_version": "1.2.0",
  "test": {
    "evaluation_time": 33.84,
    "map_at_1": 0.33841,
    "map_at_10": 0.45355,
    "map_at_100": 0.46866,
    "map_at_1000": 0.46994,
    "map_at_3": 0.41665,
    "map_at_5": 0.43594,
    "mrr_at_1": 0.41488,
    "mrr_at_10": 0.51732,
    "mrr_at_100": 0.52392,
    "mrr_at_1000": 0.52428,
    "mrr_at_3": 0.49142,
    "mrr_at_5": 0.50672,
    "ndcg_at_1": 0.41488,
    "ndcg_at_10": 0.52067,
    "ndcg_at_100": 0.57335,
    "ndcg_at_1000": 0.59114,
    "ndcg_at_3": 0.46854,
    "ndcg_at_5": 0.49007,
    "precision_at_1": 0.41488,
    "precision_at_10": 0.10014,
    "precision_at_100": 0.01584,
    "precision_at_1000": 0.00205,
    "precision_at_3": 0.22461,
    "precision_at_5": 0.16109,
    "recall_at_1": 0.33841,
    "recall_at_10": 0.64615,
    "recall_at_100": 0.86866,
    "recall_at_1000": 0.97692,
    "recall_at_3": 0.49115,
    "recall_at_5": 0.55329
  }
}