{
  "dataset_revision": null,
  "mteb_dataset_name": "ArguAna",
  "mteb_version": "1.1.2",
  "test": {
    "evaluation_time": 2.03,
    "map_at_1": 0.40541,
    "map_at_10": 0.56988,
    "map_at_100": 0.57512,
    "map_at_1000": 0.57515,
    "map_at_3": 0.52975,
    "map_at_5": 0.55596,
    "mrr_at_1": 0.41323,
    "mrr_at_10": 0.57279,
    "mrr_at_100": 0.57809,
    "mrr_at_1000": 0.57812,
    "mrr_at_3": 0.5326,
    "mrr_at_5": 0.55881,
    "ndcg_at_1": 0.40541,
    "ndcg_at_10": 0.65162,
    "ndcg_at_100": 0.67187,
    "ndcg_at_1000": 0.67256,
    "ndcg_at_3": 0.57118,
    "ndcg_at_5": 0.61838,
    "precision_at_1": 0.40541,
    "precision_at_10": 0.09075,
    "precision_at_100": 0.00991,
    "precision_at_1000": 0.001,
    "precision_at_3": 0.23044,
    "precision_at_5": 0.16117,
    "recall_at_1": 0.40541,
    "recall_at_10": 0.90754,
    "recall_at_100": 0.99147,
    "recall_at_1000": 0.99644,
    "recall_at_3": 0.69132,
    "recall_at_5": 0.80583
  }
}