{
  "dataset_revision": "c22ab2a51041ffd869aaddef7af8d8215647e41a",
  "mteb_dataset_name": "ArguAna",
  "mteb_version": "1.2.0",
  "test": {
    "evaluation_time": 13.29,
    "map_at_1": 0.37553,
    "map_at_10": 0.54654,
    "map_at_100": 0.55211,
    "map_at_1000": 0.55213,
    "map_at_3": 0.5032,
    "map_at_5": 0.53076,
    "mrr_at_1": 0.38051,
    "mrr_at_10": 0.54849,
    "mrr_at_100": 0.55399,
    "mrr_at_1000": 0.55401,
    "mrr_at_3": 0.50533,
    "mrr_at_5": 0.53204,
    "ndcg_at_1": 0.37553,
    "ndcg_at_10": 0.63226,
    "ndcg_at_100": 0.6541,
    "ndcg_at_1000": 0.6546,
    "ndcg_at_3": 0.54459,
    "ndcg_at_5": 0.59433,
    "precision_at_1": 0.37553,
    "precision_at_10": 0.09018,
    "precision_at_100": 0.00993,
    "precision_at_1000": 0.001,
    "precision_at_3": 0.22143,
    "precision_at_5": 0.15704,
    "recall_at_1": 0.37553,
    "recall_at_10": 0.90185,
    "recall_at_100": 0.99289,
    "recall_at_1000": 0.99644,
    "recall_at_3": 0.6643,
    "recall_at_5": 0.78521
  }
}