{
  "dataset_revision": "c22ab2a51041ffd869aaddef7af8d8215647e41a",
  "mteb_dataset_name": "ArguAna",
  "mteb_version": "1.2.0",
  "test": {
    "evaluation_time": 3.18,
    "map_at_1": 0.28805,
    "map_at_10": 0.45773,
    "map_at_100": 0.46589,
    "map_at_1000": 0.46593,
    "map_at_3": 0.40612,
    "map_at_5": 0.43684,
    "mrr_at_1": 0.29232,
    "mrr_at_10": 0.45966,
    "mrr_at_100": 0.46775,
    "mrr_at_1000": 0.46779,
    "mrr_at_3": 0.40813,
    "mrr_at_5": 0.43857,
    "ndcg_at_1": 0.28805,
    "ndcg_at_10": 0.55197,
    "ndcg_at_100": 0.5846,
    "ndcg_at_1000": 0.58547,
    "ndcg_at_3": 0.44601,
    "ndcg_at_5": 0.50123,
    "precision_at_1": 0.28805,
    "precision_at_10": 0.08528,
    "precision_at_100": 0.0099,
    "precision_at_1000": 0.001,
    "precision_at_3": 0.18729,
    "precision_at_5": 0.13912,
    "recall_at_1": 0.28805,
    "recall_at_10": 0.85277,
    "recall_at_100": 0.99004,
    "recall_at_1000": 0.99644,
    "recall_at_3": 0.56188,
    "recall_at_5": 0.69559
  }
}