{
  "dataset_revision": null,
  "mteb_dataset_name": "ArguAna",
  "mteb_version": "1.1.2",
  "test": {
    "evaluation_time": 2.0,
    "map_at_1": 0.37198,
    "map_at_10": 0.54358,
    "map_at_100": 0.54914,
    "map_at_1000": 0.54917,
    "map_at_3": 0.50119,
    "map_at_5": 0.52775,
    "mrr_at_1": 0.38122,
    "mrr_at_10": 0.54727,
    "mrr_at_100": 0.55269,
    "mrr_at_1000": 0.55272,
    "mrr_at_3": 0.50486,
    "mrr_at_5": 0.53118,
    "ndcg_at_1": 0.37198,
    "ndcg_at_10": 0.62958,
    "ndcg_at_100": 0.65153,
    "ndcg_at_1000": 0.65222,
    "ndcg_at_3": 0.54394,
    "ndcg_at_5": 0.5916,
    "precision_at_1": 0.37198,
    "precision_at_10": 0.08997,
    "precision_at_100": 0.00991,
    "precision_at_1000": 0.001,
    "precision_at_3": 0.22262,
    "precision_at_5": 0.15661,
    "recall_at_1": 0.37198,
    "recall_at_10": 0.89972,
    "recall_at_100": 0.99147,
    "recall_at_1000": 0.99644,
    "recall_at_3": 0.66785,
    "recall_at_5": 0.78307
  }
}