{
  "dataset_revision": "4ffe81d471b1924886b33c7567bfb200e9eec5c4",
  "mteb_dataset_name": "CQADupstackWordpressRetrieval",
  "mteb_version": "1.2.0",
  "test": {
    "evaluation_time": 58.92,
    "map_at_1": 0.24036,
    "map_at_10": 0.3305,
    "map_at_100": 0.33929,
    "map_at_1000": 0.3404,
    "map_at_3": 0.30589,
    "map_at_5": 0.31811,
    "mrr_at_1": 0.26063,
    "mrr_at_10": 0.35219,
    "mrr_at_100": 0.35949,
    "mrr_at_1000": 0.3603,
    "mrr_at_3": 0.33025,
    "mrr_at_5": 0.34088,
    "ndcg_at_1": 0.26063,
    "ndcg_at_10": 0.38181,
    "ndcg_at_100": 0.42478,
    "ndcg_at_1000": 0.45117,
    "ndcg_at_3": 0.33492,
    "ndcg_at_5": 0.35393,
    "precision_at_1": 0.26063,
    "precision_at_10": 0.06007,
    "precision_at_100": 0.00871,
    "precision_at_1000": 0.00122,
    "precision_at_3": 0.14603,
    "precision_at_5": 0.09982,
    "recall_at_1": 0.24036,
    "recall_at_10": 0.51819,
    "recall_at_100": 0.71489,
    "recall_at_1000": 0.9073,
    "recall_at_3": 0.38974,
    "recall_at_5": 0.43504
  }
}