{
  "dataset_revision": "eea2b4fe26a775864c896887d910b76a8098ad3f",
  "mteb_dataset_name": "STS22",
  "mteb_version": "1.1.2",
  "test": {
    "en": {
      "cos_sim": {
        "pearson": 0.6878487224369206,
        "spearman": 0.6948614015419026
      },
      "euclidean": {
        "pearson": 0.7066587467352807,
        "spearman": 0.6968773443979303
      },
      "manhattan": {
        "pearson": 0.7040076283855855,
        "spearman": 0.6854588226901919
      }
    },
    "evaluation_time": 0.07
  }
}