{
  "dataset_revision": "6c6430d3a6d36f8d2a829195bc5dc94d7e063e53",
  "mteb_dataset_name": "CQADupstackUnixRetrieval",
  "mteb_version": "1.2.0",
  "test": {
    "evaluation_time": 62.73,
    "map_at_1": 0.28969,
    "map_at_10": 0.38761,
    "map_at_100": 0.39865,
    "map_at_1000": 0.39956,
    "map_at_3": 0.35785,
    "map_at_5": 0.37484,
    "mrr_at_1": 0.34142,
    "mrr_at_10": 0.43152,
    "mrr_at_100": 0.43904,
    "mrr_at_1000": 0.43955,
    "mrr_at_3": 0.40594,
    "mrr_at_5": 0.42021,
    "ndcg_at_1": 0.34142,
    "ndcg_at_10": 0.44555,
    "ndcg_at_100": 0.49568,
    "ndcg_at_1000": 0.51667,
    "ndcg_at_3": 0.39257,
    "ndcg_at_5": 0.41749,
    "precision_at_1": 0.34142,
    "precision_at_10": 0.07481,
    "precision_at_100": 0.01136,
    "precision_at_1000": 0.00143,
    "precision_at_3": 0.17755,
    "precision_at_5": 0.12481,
    "recall_at_1": 0.28969,
    "recall_at_10": 0.57841,
    "recall_at_100": 0.79581,
    "recall_at_1000": 0.94242,
    "recall_at_3": 0.4347,
    "recall_at_5": 0.49671
  }
}