{
  "dataset_revision": "6c6430d3a6d36f8d2a829195bc5dc94d7e063e53",
  "mteb_dataset_name": "CQADupstackUnixRetrieval",
  "mteb_version": "1.2.0",
  "test": {
    "evaluation_time": 60.13,
    "map_at_1": 0.26861,
    "map_at_10": 0.36827,
    "map_at_100": 0.37927,
    "map_at_1000": 0.38023,
    "map_at_3": 0.33501,
    "map_at_5": 0.35487,
    "mrr_at_1": 0.3181,
    "mrr_at_10": 0.41131,
    "mrr_at_100": 0.41922,
    "mrr_at_1000": 0.41976,
    "mrr_at_3": 0.38277,
    "mrr_at_5": 0.39961,
    "ndcg_at_1": 0.3181,
    "ndcg_at_10": 0.42777,
    "ndcg_at_100": 0.47782,
    "ndcg_at_1000": 0.499,
    "ndcg_at_3": 0.36855,
    "ndcg_at_5": 0.39874,
    "precision_at_1": 0.3181,
    "precision_at_10": 0.07295,
    "precision_at_100": 0.01112,
    "precision_at_1000": 0.0014,
    "precision_at_3": 0.16698,
    "precision_at_5": 0.12127,
    "recall_at_1": 0.26861,
    "recall_at_10": 0.56647,
    "recall_at_100": 0.78274,
    "recall_at_1000": 0.92877,
    "recall_at_3": 0.40854,
    "recall_at_5": 0.4826
  }
}