{
  "dataset_revision": "65ac3a16b8e91f9cee4c9828cc7c335575432a2a",
  "mteb_dataset_name": "CQADupstackStatsRetrieval",
  "mteb_version": "1.2.0",
  "test": {
    "evaluation_time": 45.25,
    "map_at_1": 0.29137,
    "map_at_10": 0.35878,
    "map_at_100": 0.36831,
    "map_at_1000": 0.36923,
    "map_at_3": 0.33614,
    "map_at_5": 0.34825,
    "mrr_at_1": 0.32975,
    "mrr_at_10": 0.39076,
    "mrr_at_100": 0.39866,
    "mrr_at_1000": 0.39931,
    "mrr_at_3": 0.37014,
    "mrr_at_5": 0.38165,
    "ndcg_at_1": 0.32975,
    "ndcg_at_10": 0.40153,
    "ndcg_at_100": 0.44859,
    "ndcg_at_1000": 0.47217,
    "ndcg_at_3": 0.35852,
    "ndcg_at_5": 0.37789,
    "precision_at_1": 0.32975,
    "precision_at_10": 0.06196,
    "precision_at_100": 0.00936,
    "precision_at_1000": 0.00121,
    "precision_at_3": 0.14928,
    "precision_at_5": 0.10245,
    "recall_at_1": 0.29137,
    "recall_at_10": 0.50261,
    "recall_at_100": 0.72013,
    "recall_at_1000": 0.89473,
    "recall_at_3": 0.38369,
    "recall_at_5": 0.43265
  }
}