{
  "dataset_revision": "ad9991cb51e31e31e430383c75ffb2885547b5f0",
  "mteb_dataset_name": "CQADupstackEnglishRetrieval",
  "mteb_version": "1.2.0",
  "test": {
    "evaluation_time": 41.0,
    "map_at_1": 0.3188,
    "map_at_10": 0.42393,
    "map_at_100": 0.43644,
    "map_at_1000": 0.43779,
    "map_at_3": 0.39428,
    "map_at_5": 0.4104,
    "mrr_at_1": 0.39809,
    "mrr_at_10": 0.48297,
    "mrr_at_100": 0.48935,
    "mrr_at_1000": 0.4898,
    "mrr_at_3": 0.46221,
    "mrr_at_5": 0.47329,
    "ndcg_at_1": 0.39809,
    "ndcg_at_10": 0.48076,
    "ndcg_at_100": 0.5237,
    "ndcg_at_1000": 0.54397,
    "ndcg_at_3": 0.44136,
    "ndcg_at_5": 0.45812,
    "precision_at_1": 0.39809,
    "precision_at_10": 0.09121,
    "precision_at_100": 0.01456,
    "precision_at_1000": 0.00194,
    "precision_at_3": 0.21444,
    "precision_at_5": 0.15006,
    "recall_at_1": 0.3188,
    "recall_at_10": 0.57825,
    "recall_at_100": 0.76025,
    "recall_at_1000": 0.88611,
    "recall_at_3": 0.45748,
    "recall_at_5": 0.50821
  }
}