{
  "dataset_revision": "4ffe81d471b1924886b33c7567bfb200e9eec5c4",
  "mteb_dataset_name": "CQADupstackWordpressRetrieval",
  "mteb_version": "1.2.0",
  "test": {
    "evaluation_time": 61.73,
    "map_at_1": 0.24871,
    "map_at_10": 0.33765,
    "map_at_100": 0.34652,
    "map_at_1000": 0.34753,
    "map_at_3": 0.31144,
    "map_at_5": 0.32576,
    "mrr_at_1": 0.26987,
    "mrr_at_10": 0.35958,
    "mrr_at_100": 0.36717,
    "mrr_at_1000": 0.36792,
    "mrr_at_3": 0.33672,
    "mrr_at_5": 0.34827,
    "ndcg_at_1": 0.26987,
    "ndcg_at_10": 0.38865,
    "ndcg_at_100": 0.43289,
    "ndcg_at_1000": 0.45842,
    "ndcg_at_3": 0.33848,
    "ndcg_at_5": 0.36089,
    "precision_at_1": 0.26987,
    "precision_at_10": 0.06063,
    "precision_at_100": 0.00891,
    "precision_at_1000": 0.00123,
    "precision_at_3": 0.14418,
    "precision_at_5": 0.10092,
    "recall_at_1": 0.24871,
    "recall_at_10": 0.52471,
    "recall_at_100": 0.72894,
    "recall_at_1000": 0.91836,
    "recall_at_3": 0.38715,
    "recall_at_5": 0.44033
  }
}