{
  "dataset_revision": "0228b52cf27578f30900b9e5271d331663a030d7",
  "mteb_dataset_name": "SciFact",
  "mteb_version": "1.2.0",
  "test": {
    "evaluation_time": 5.73,
    "map_at_1": 0.60594,
    "map_at_10": 0.70121,
    "map_at_100": 0.70673,
    "map_at_1000": 0.70688,
    "map_at_3": 0.66769,
    "map_at_5": 0.69102,
    "mrr_at_1": 0.63333,
    "mrr_at_10": 0.70885,
    "mrr_at_100": 0.71289,
    "mrr_at_1000": 0.71303,
    "mrr_at_3": 0.68222,
    "mrr_at_5": 0.70089,
    "ndcg_at_1": 0.63333,
    "ndcg_at_10": 0.74566,
    "ndcg_at_100": 0.76796,
    "ndcg_at_1000": 0.77133,
    "ndcg_at_3": 0.68963,
    "ndcg_at_5": 0.72461,
    "precision_at_1": 0.63333,
    "precision_at_10": 0.099,
    "precision_at_100": 0.01103,
    "precision_at_1000": 0.00113,
    "precision_at_3": 0.26778,
    "precision_at_5": 0.18267,
    "recall_at_1": 0.60594,
    "recall_at_10": 0.87422,
    "recall_at_100": 0.975,
    "recall_at_1000": 1.0,
    "recall_at_3": 0.72472,
    "recall_at_5": 0.81356
  }
}